asyncsector/__init__.py
asyncsector/__main__.py
asyncsector/asyncsector.py
asyncsector/util.py
asyncsector-0.2.1.dist-info/LICENSE.md
asyncsector-0.2.1.dist-info/METADATA
asyncsector-0.2.1.dist-info/WHEEL
asyncsector-0.2.1.dist-info/entry_points.txt
asyncsector-0.2.1.dist-info/top_level.txt
asyncsector-0.2.1.dist-info/RECORD
