Metadata-Version: 2.1
Name: asyncsector
Version: 0.2.1
Summary: Asynchronous package for Sector Alarm
Home-page: https://github.com/mgejke/asyncsector
Author: Martin Gejke
Author-email: martin@gejke.se
License: BSD
Requires-Dist: aiohttp (==3.4.4)
